[{"Name":"\u4F5C\u696D\u53F0","IconResourcesPath":"Textures/icon_2D_workbench","Type":1000,"ReferenceID":1000,"MaxCount":999,"ID":1},{"Name":"\u304B\u307E\u3069","IconResourcesPath":"Textures/icon_2D_kamado","Type":1001,"ReferenceID":1001,"MaxCount":999,"ID":2},{"Name":"\u77F3\u306E\u30D6\u30ED\u30C3\u30AF","IconResourcesPath":"Textures/block_2d_001","Type":1,"ReferenceID":1001,"MaxCount":9999,"ID":101},{"Name":"\u6728\u306E\u30D6\u30ED\u30C3\u30AFA","IconResourcesPath":"Textures/block_2d_002","Type":1,"ReferenceID":1002,"MaxCount":9999,"ID":102},{"Name":"\u6728\u306E\u30D6\u30ED\u30C3\u30AFB","IconResourcesPath":"Textures/block_2d_003","Type":1,"ReferenceID":1003,"MaxCount":9999,"ID":103},{"Name":"\u6728\u306E\u30D6\u30ED\u30C3\u30AFC","IconResourcesPath":"Textures/block_2d_004","Type":1,"ReferenceID":1004,"MaxCount":9999,"ID":104},{"Name":"\u571F\u306E\u30D6\u30ED\u30C3\u30AF","IconResourcesPath":"Textures/block_2d_005","Type":1,"ReferenceID":1005,"MaxCount":9999,"ID":105},{"Name":"\u8349\u571F\u306E\u30D6\u30ED\u30C3\u30AF","IconResourcesPath":"Textures/block_2d_006","Type":1,"ReferenceID":1006,"MaxCount":9999,"ID":106},{"Name":"\u77F3\u30EC\u30F3\u30AC\u306E\u30D6\u30ED\u30C3\u30AF","IconResourcesPath":"Textures/block_2d_007","Type":1,"ReferenceID":1007,"MaxCount":9999,"ID":107},{"Name":"\u7802\u306E\u30D6\u30ED\u30C3\u30AF","IconResourcesPath":"Textures/block_2d_008","Type":1,"ReferenceID":1008,"MaxCount":9999,"ID":108},{"Name":"\u9285\u306E\u30D6\u30ED\u30C3\u30AF","IconResourcesPath":"Textures/block_2d_011","Type":1,"ReferenceID":1009,"MaxCount":9999,"ID":109},{"Name":"\u9280\u306E\u30D6\u30ED\u30C3\u30AF","IconResourcesPath":"Textures/block_2d_010","Type":1,"ReferenceID":1010,"MaxCount":9999,"ID":110},{"Name":"\u91D1\u306E\u30D6\u30ED\u30C3\u30AF","IconResourcesPath":"Textures/block_2d_009","Type":1,"ReferenceID":1011,"MaxCount":9999,"ID":111},{"Name":"\u8449\u306E\u30D6\u30ED\u30C3\u30AF","IconResourcesPath":"Textures/block_2d_012","Type":1,"ReferenceID":1012,"MaxCount":9999,"ID":112},{"Name":"\u6728\u6750","IconResourcesPath":"Textures/matter_2d_001","Type":2,"ReferenceID":-1,"MaxCount":9999,"ID":1001},{"Name":"\u8449","IconResourcesPath":"Textures/matter_2d_002","Type":2,"ReferenceID":-1,"MaxCount":9999,"ID":1002},{"Name":"\u77F3\u6750","IconResourcesPath":"Textures/matter_2d_003","Type":2,"ReferenceID":-1,"MaxCount":9999,"ID":1003},{"Name":"\u9285\u9271\u77F3","IconResourcesPath":"Textures/matter_2d_004","Type":2,"ReferenceID":-1,"MaxCount":9999,"ID":1004},{"Name":"\u9244\u9271\u77F3","IconResourcesPath":"Textures/matter_2d_005","Type":2,"ReferenceID":-1,"MaxCount":9999,"ID":1005},{"Name":"\u9280\u9271\u77F3","IconResourcesPath":"Textures/matter_2d_006","Type":2,"ReferenceID":-1,"MaxCount":9999,"ID":1006},{"Name":"\u91D1\u9271\u77F3","IconResourcesPath":"Textures/matter_2d_007","Type":2,"ReferenceID":-1,"MaxCount":9999,"ID":1007},{"Name":"\u9285\u306E\u5EF6\u68D2","IconResourcesPath":"Textures/matter_2d_008","Type":2,"ReferenceID":-1,"MaxCount":9999,"ID":1008},{"Name":"\u9244\u306E\u5EF6\u68D2","IconResourcesPath":"Textures/matter_2d_009","Type":2,"ReferenceID":-1,"MaxCount":9999,"ID":1009},{"Name":"\u9280\u306E\u5EF6\u68D2","IconResourcesPath":"Textures/matter_2d_010","Type":2,"ReferenceID":-1,"MaxCount":9999,"ID":1010},{"Name":"\u91D1\u306E\u5EF6\u68D2","IconResourcesPath":"Textures/matter_2d_011","Type":2,"ReferenceID":-1,"MaxCount":9999,"ID":1011},{"Name":"\u571F","IconResourcesPath":"Textures/matter_2d_012","Type":2,"ReferenceID":-1,"MaxCount":9999,"ID":1012},{"Name":"\u7802","IconResourcesPath":"Textures/matter_2d_013","Type":2,"ReferenceID":-1,"MaxCount":9999,"ID":1013},{"Name":"\u30D3\u30EB\u30C0\u30FC\u30DA\u30F3\u30B7\u30EB","IconResourcesPath":"Textures/pen","Type":50,"ReferenceID":-1,"MaxCount":1,"ID":3000},{"Name":"\u7A7A\u306E\u8A2D\u8A08\u56F3","IconResourcesPath":"Textures/icon_2D_blueprint_01","Type":51,"ReferenceID":-1,"MaxCount":9999,"ID":3001},{"Name":"\u8A2D\u8A08\u56F3","IconResourcesPath":"Textures/icon_2D_blueprint_02","Type":52,"ReferenceID":-1,"MaxCount":1,"ID":3002}]