[{"BonusList01":"50001,50002,50003","Percent01":100,"BonusList02":"N","Percent02":-1,"BonusList03":"N","Percent03":-1,"BonusList04":"N","Percent04":-1,"ID":1},{"BonusList01":"50004,50005,50006","Percent01":100,"BonusList02":"N","Percent02":-1,"BonusList03":"N","Percent03":-1,"BonusList04":"N","Percent04":-1,"ID":2},{"BonusList01":"50001,50002,50003,50004,50005,50006","Percent01":100,"BonusList02":"N","Percent02":-1,"BonusList03":"N","Percent03":-1,"BonusList04":"N","Percent04":-1,"ID":3},{"BonusList01":"50001,50002,50003","Percent01":45,"BonusList02":"50004,50005,50006","Percent02":45,"BonusList03":"60001,60002,60003,60004,60005,60006","Percent03":10,"BonusList04":"N","Percent04":-1,"ID":4},{"BonusList01":"60001,60002,60003,60004,60005,60006","Percent01":100,"BonusList02":"N","Percent02":-1,"BonusList03":"N","Percent03":-1,"BonusList04":"N","Percent04":-1,"ID":5}]